{"files": {"equipment_py": {"index": {"relative_filename": "equipment.py", "html_filename": "equipment_py.html", "nums": [1, 1, 0, 0, 0, 0, 0]}, "hash": "b6ead59634135dfc5cb43d2ab815dc53"}, "process_ArrayParsing_py": {"index": {"relative_filename": "process/ArrayParsing.py", "html_filename": "process_ArrayParsing_py.html", "nums": [1, 98, 0, 4, 36, 3, 3]}, "hash": "9874339072208ae0ac0aecd2b8dfff60"}, "utils_py": {"index": {"relative_filename": "utils.py", "html_filename": "utils_py.html", "nums": [1, 1, 0, 0, 0, 0, 0]}, "hash": "2fabff74680c6860cf264a52cb262335"}, "process_TextParsing_py": {"index": {"relative_filename": "process/TextParsing.py", "html_filename": "process_TextParsing_py.html", "nums": [1, 41, 0, 7, 10, 1, 1]}, "hash": "8159d69aeeb2e3770ba16a5163ef8d21"}, "__init___py": {"index": {"relative_filename": "__init__.py", "html_filename": "__init___py.html", "nums": [1, 0, 0, 0, 0, 0, 0]}, "hash": "4911cff48f6b9e153df4c1a3ecaded19"}, "process_py": {"index": {"relative_filename": "process.py", "html_filename": "process_py.html", "nums": [1, 1, 0, 0, 0, 0, 0]}, "hash": "b6ead59634135dfc5cb43d2ab815dc53"}, "equipment_Equipment_py": {"index": {"relative_filename": "equipment/Equipment.py", "html_filename": "equipment_Equipment_py.html", "nums": [1, 88, 0, 13, 38, 5, 7]}, "hash": "189f5d1c2f97234e5f7c63a85509e498"}, "equipment_feature_py": {"index": {"relative_filename": "equipment/feature.py", "html_filename": "equipment_feature_py.html", "nums": [1, 1, 0, 0, 0, 0, 0]}, "hash": "b6ead59634135dfc5cb43d2ab815dc53"}, "__main___py": {"index": {"relative_filename": "__main__.py", "html_filename": "__main___py.html", "nums": [1, 48, 0, 48, 20, 0, 20]}, "hash": "512daa56555744cc85ba0ce7c6c9292a"}, "equipment_feature_Interface_py": {"index": {"relative_filename": "equipment/feature/Interface.py", "html_filename": "equipment_feature_Interface_py.html", "nums": [1, 28, 0, 0, 8, 0, 0]}, "hash": "52d9ae2583f3a3424b9ae2b15b4eeeda"}, "process_ListParsing_py": {"index": {"relative_filename": "process/ListParsing.py", "html_filename": "process_ListParsing_py.html", "nums": [1, 76, 0, 6, 16, 2, 2]}, "hash": "ba36dd4225dbe6df51c6c63e9b5296dc"}, "utils_ExcelWorkbookManager_py": {"index": {"relative_filename": "utils/ExcelWorkbookManager.py", "html_filename": "utils_ExcelWorkbookManager_py.html", "nums": [1, 30, 0, 3, 2, 1, 1]}, "hash": "a1ef2075a6201c43ca0fb278bf763d42"}}, "format": 1, "version": "4.0", "settings": "22c8502efc93bfac405c79b4051fe55c"}